nonebot_plugin_web_bottle-1.6.0.dist-info/METADATA
nonebot_plugin_web_bottle-1.6.0.dist-info/WHEEL
nonebot_plugin_web_bottle-1.6.0.dist-info/entry_points.txt
nonebot_plugin_web_bottle-1.6.0.dist-info/licenses/LICENSE.txt
nonebot_plugin_web_bottle/.idea/.gitignore
nonebot_plugin_web_bottle/.idea/.name
nonebot_plugin_web_bottle/.idea/inspectionProfiles/Project_Default.xml
nonebot_plugin_web_bottle/.idea/inspectionProfiles/profiles_settings.xml
nonebot_plugin_web_bottle/.idea/misc.xml
nonebot_plugin_web_bottle/.idea/modules.xml
nonebot_plugin_web_bottle/.idea/nonebot_plugin_web_bottle.iml
nonebot_plugin_web_bottle/.idea/workspace.xml
nonebot_plugin_web_bottle/__init__.py
nonebot_plugin_web_bottle/config.py
nonebot_plugin_web_bottle/data_deal.py
nonebot_plugin_web_bottle/templates/comments.html
nonebot_plugin_web_bottle/templates/index.html
nonebot_plugin_web_bottle/templates/login/1.html
nonebot_plugin_web_bottle/templates/login/login.html
nonebot_plugin_web_bottle/templates/login/static/css/backend.css
nonebot_plugin_web_bottle/templates/login/static/font/qiantu.ttf
nonebot_plugin_web_bottle/templates/login/static/image/background.png
nonebot_plugin_web_bottle/templates/login/static/images/background.jpg
nonebot_plugin_web_bottle/templates/login/static/images/background.webp
nonebot_plugin_web_bottle/templates/login/static/images/background2.png
nonebot_plugin_web_bottle/templates/login/static/images/background2.webp
nonebot_plugin_web_bottle/templates/login/static/images/linglan.png
nonebot_plugin_web_bottle/templates/login/static/images/linglan.webp
nonebot_plugin_web_bottle/templates/login/static/images/luoxiqi.png
nonebot_plugin_web_bottle/templates/login/static/images/luoxiqi.webp
nonebot_plugin_web_bottle/templates/login/static/images/xilufei.png
nonebot_plugin_web_bottle/templates/login/static/images/xilufei.webp
nonebot_plugin_web_bottle/templates/login/static/js1/backend-bundle.min.js
nonebot_plugin_web_bottle/templates/login/static/picture/linglan.png
nonebot_plugin_web_bottle/templates/login/static/picture/luoxiqi.png
nonebot_plugin_web_bottle/templates/login/static/picture/xilufei.png
nonebot_plugin_web_bottle/templates/login/static/styles.css
nonebot_plugin_web_bottle-1.6.0.dist-info/RECORD
