Metadata-Version: 2.1
Name: nonebot_plugin_web_bottle
Version: 1.6.0
Summary: 有web的漂流瓶
Author-Email: Xican <723926109@qq.com>
License: MIT
Project-URL: homepage, https://github.com/luosheng520qaq/nonebot-plugin-web-bottle/
Project-URL: repository, https://github.com/luosheng520qaq/nonebot-plugin-web-bottle/
Requires-Python: >=3.10
Requires-Dist: aiofiles>=23.2.1
Requires-Dist: httpx>=0.23.0
Requires-Dist: nonebot-plugin-localstore>=0.7.1
Requires-Dist: nonebot-adapter-onebot>=2.4.4
Requires-Dist: nonebot2[fastapi]>=2.3.2
Requires-Dist: jinja2>=3.1.4
Requires-Dist: pillow>=11.0.0
Requires-Dist: cryptography
Requires-Dist: itsdangerous>=2.2.0
Requires-Dist: python-multipart>=0.0.20
Requires-Dist: fastapi>=0.110.0
Requires-Dist: pydantic>=1.10.11
